[
  {
    "id": 1,
    "title": "Fortnite Season 10 Ultimate Guide - All New Mechanics",
    "description": "Learn all the new mechanics and features in Fortnite Season 10 with this comprehensive guide. Master the new weapons, map changes, and strategies to dominate in battle royale.",
    "thumbnailUrl": "https://images.unsplash.com/photo-1560253023-3ec5d502959f?auto=format&fit=crop&w=640&h=360",
    "videoUrl": "https://www.youtube.com/watch?v=dQw4w9WgXcQ",
    "duration": 862,
    "views": 1200000,
    "gameId": 1,
    "channelId": 1,
    "createdAt": "2023-06-10T12:30:00Z"
  },
  {
    "id": 2,
    "title": "League of Legends Pro Tips - Climb to Diamond Fast",
    "description": "Professional LoL player shares secret techniques to rank up quickly in Season 13. Learn advanced wave management, vision control, and team fighting strategies.",
    "thumbnailUrl": "https://images.unsplash.com/photo-1542751371-adc38448a05e?auto=format&fit=crop&w=640&h=360",
    "videoUrl": "https://www.youtube.com/watch?v=dQw4w9WgXcQ",
    "duration": 1375,
    "views": 856000,
    "gameId": 4,
    "channelId": 3,
    "createdAt": "2023-06-17T14:45:00Z"
  },
  {
    "id": 3,
    "title": "Minecraft: 10 Building Tricks Only Pros Know",
    "description": "Take your Minecraft building skills to the next level with these 10 advanced building techniques that most players don't know about. Create stunning structures with these pro tips.",
    "thumbnailUrl": "https://images.unsplash.com/photo-1624085367917-a0b02e7ca8a1?auto=format&fit=crop&w=640&h=360",
    "videoUrl": "https://www.youtube.com/watch?v=dQw4w9WgXcQ",
    "duration": 1083,
    "views": 2300000,
    "gameId": 2,
    "channelId": 4,
    "createdAt": "2023-05-30T09:15:00Z"
  },
  {
    "id": 4,
    "title": "Call of Duty Warzone: Best Loadouts Guide 2023",
    "description": "Dominate in Call of Duty Warzone with these meta loadouts for all playstyles. Detailed weapon builds, perk selections, and tactical equipment choices to give you the edge in combat.",
    "thumbnailUrl": "https://images.unsplash.com/photo-1602673221577-0b56d7ce446b?auto=format&fit=crop&w=640&h=360",
    "videoUrl": "https://www.youtube.com/watch?v=dQw4w9WgXcQ",
    "duration": 765,
    "views": 1500000,
    "gameId": 3,
    "channelId": 2,
    "createdAt": "2023-06-19T08:20:00Z"
  },
  {
    "id": 5,
    "title": "Valorant: Ultimate Aim Training Routine (All Agents)",
    "description": "Improve your aim drastically with this comprehensive training routine designed for Valorant. Covers all agents and weapon types with specific drills to master each aspect of aiming.",
    "thumbnailUrl": "https://images.unsplash.com/photo-1603481546239-65e837a9ef5a?auto=format&fit=crop&w=640&h=360",
    "videoUrl": "https://www.youtube.com/watch?v=dQw4w9WgXcQ",
    "duration": 1517,
    "views": 987000,
    "gameId": 5,
    "channelId": 6,
    "createdAt": "2023-05-15T16:30:00Z"
  },
  {
    "id": 6,
    "title": "Apex Legends: How to Rank Up Fast (Season 16)",
    "description": "Detailed strategies to climb the ranked ladder in Apex Legends Season 16. Learn optimal drop locations, legend synergies, and endgame tactics from a Predator player.",
    "thumbnailUrl": "https://images.unsplash.com/photo-1550745165-9bc0b252726f?auto=format&fit=crop&w=640&h=360",
    "videoUrl": "https://www.youtube.com/watch?v=dQw4w9WgXcQ",
    "duration": 989,
    "views": 722000,
    "gameId": 6,
    "channelId": 5,
    "createdAt": "2023-06-05T11:40:00Z"
  },
  {
    "id": 7,
    "title": "Fortnite: Advanced Building Techniques for Chapter 4",
    "description": "Master the most advanced building and editing techniques in Fortnite Chapter 4. Learn piece control, boxfighting, and retake strategies from one of the top builders in the game.",
    "thumbnailUrl": "https://images.unsplash.com/photo-1580327344181-c1163234e5a0?auto=format&fit=crop&w=640&h=360",
    "videoUrl": "https://www.youtube.com/watch?v=dQw4w9WgXcQ",
    "duration": 1242,
    "views": 1800000,
    "gameId": 1,
    "channelId": 1,
    "createdAt": "2023-06-15T13:50:00Z"
  },
  {
    "id": 8,
    "title": "Ultimate Gaming PC Build Guide 2023 (Budget to High-End)",
    "description": "Complete walkthrough of building a gaming PC in 2023, with options for every budget. Includes component selection, assembly tips, and optimization settings for maximum performance.",
    "thumbnailUrl": "https://images.unsplash.com/photo-1612287230202-1ff1d85d1bdf?auto=format&fit=crop&w=640&h=360",
    "videoUrl": "https://www.youtube.com/watch?v=dQw4w9WgXcQ",
    "duration": 1930,
    "views": 3400000,
    "gameId": 10,
    "channelId": 2,
    "createdAt": "2023-04-20T10:15:00Z"
  },
  {
    "id": 9,
    "title": "GTA V: Hidden Easter Eggs and Secrets You Missed",
    "description": "Discover the most obscure and fascinating Easter eggs hidden throughout Los Santos in GTA V. From alien references to movie tributes, these secrets will make you see the game in a new light.",
    "thumbnailUrl": "https://images.unsplash.com/photo-1593277992013-b85473a4d200?auto=format&fit=crop&w=640&h=360",
    "videoUrl": "https://www.youtube.com/watch?v=dQw4w9WgXcQ",
    "duration": 1354,
    "views": 1650000,
    "gameId": 8,
    "channelId": 5,
    "createdAt": "2023-05-25T18:20:00Z"
  },
  {
    "id": 10,
    "title": "PUBG: Pro Movement Techniques You Should Be Using",
    "description": "Learn the advanced movement techniques used by professional PUBG players. Master peek shots, jiggle peeking, and positioning to gain a significant advantage over your opponents.",
    "thumbnailUrl": "https://images.unsplash.com/photo-1579468118864-1b9ea3c0db4a?auto=format&fit=crop&w=640&h=360",
    "videoUrl": "https://www.youtube.com/watch?v=dQw4w9WgXcQ",
    "duration": 875,
    "views": 945000,
    "gameId": 7,
    "channelId": 2,
    "createdAt": "2023-06-12T09:10:00Z"
  },
  {
    "id": 11,
    "title": "Cyberpunk 2077: Ultimate Character Build Guide (After Patch 2.0)",
    "description": "Discover the most powerful character builds in Cyberpunk 2077 after the massive 2.0 update. Detailed attribute distributions, perk selections, and gear recommendations for each playstyle.",
    "thumbnailUrl": "https://images.unsplash.com/photo-1605810230434-7631ac76ec81?auto=format&fit=crop&w=640&h=360",
    "videoUrl": "https://www.youtube.com/watch?v=dQw4w9WgXcQ",
    "duration": 1628,
    "views": 1120000,
    "gameId": 9,
    "channelId": 4,
    "createdAt": "2023-06-01T15:30:00Z"
  },
  {
    "id": 12,
    "title": "Minecraft Redstone: Automated Farm Tutorial (Works in 1.20)",
    "description": "Step-by-step tutorial to build an efficient automated farm in Minecraft 1.20. This farm works for multiple crop types and requires minimal maintenance after setup.",
    "thumbnailUrl": "https://images.unsplash.com/photo-1511512578047-dfb367046420?auto=format&fit=crop&w=640&h=360",
    "videoUrl": "https://www.youtube.com/watch?v=dQw4w9WgXcQ",
    "duration": 1455,
    "views": 1950000,
    "gameId": 2,
    "channelId": 4,
    "createdAt": "2023-05-18T11:25:00Z"
  },
  {
    "id": 13,
    "title": "Valorant: Complete Guide to Mastering Chamber",
    "description": "Master Chamber in Valorant with this comprehensive agent guide. Learn optimal teleport placements, economy management, and advanced sniper techniques specific to Chamber.",
    "thumbnailUrl": "https://images.unsplash.com/photo-1605979399824-ea3f7ea3d8cb?auto=format&fit=crop&w=640&h=360",
    "videoUrl": "https://www.youtube.com/watch?v=dQw4w9WgXcQ",
    "duration": 1267,
    "views": 832000,
    "gameId": 5,
    "channelId": 6,
    "createdAt": "2023-06-08T14:15:00Z"
  },
  {
    "id": 14,
    "title": "League of Legends: Jungle Pathing Masterclass",
    "description": "Learn optimal jungle routes and pathing strategies for every matchup in League of Legends. Maximize your efficiency and impact as a jungler with these pro techniques.",
    "thumbnailUrl": "https://images.unsplash.com/photo-1624913503273-5f9c4e980dba?auto=format&fit=crop&w=640&h=360",
    "videoUrl": "https://www.youtube.com/watch?v=dQw4w9WgXcQ",
    "duration": 1843,
    "views": 765000,
    "gameId": 4,
    "channelId": 3,
    "createdAt": "2023-05-22T09:45:00Z"
  },
  {
    "id": 15,
    "title": "Apex Legends: Advanced Movement Guide (Tap Strafing, Super Glides)",
    "description": "Master the most advanced movement techniques in Apex Legends including tap strafing, super glides, and wall bounces. Increase your mobility and outplay opponents with these pro moves.",
    "thumbnailUrl": "https://images.unsplash.com/photo-1580327344181-c1163234e5a0?auto=format&fit=crop&w=640&h=360",
    "videoUrl": "https://www.youtube.com/watch?v=dQw4w9WgXcQ",
    "duration": 1198,
    "views": 915000,
    "gameId": 6,
    "channelId": 5,
    "createdAt": "2023-06-14T16:50:00Z"
  },
  {
    "id": 16,
    "title": "Call of Duty: Pro Sniper Tips and Tricks",
    "description": "Improve your sniping skills in Call of Duty with these professional techniques. Learn about positioning, quickscoping, and handling various sniper rifles effectively.",
    "thumbnailUrl": "https://images.unsplash.com/photo-1614294149010-950b698f72c0?auto=format&fit=crop&w=640&h=360",
    "videoUrl": "https://www.youtube.com/watch?v=dQw4w9WgXcQ",
    "duration": 1021,
    "views": 1380000,
    "gameId": 3,
    "channelId": 2,
    "createdAt": "2023-05-28T13:20:00Z"
  }
]
